haunt/__init__.py
haunt/_registry.py
haunt/exceptions.py
haunt/models.py
haunt/_cli/__init__.py
haunt/_cli/cli.py
haunt/_cli/output.py
haunt/_files/__init__.py
haunt/_files/cleanup.py
haunt/_files/discover.py
haunt/_files/paths.py
haunt/_files/symlinks.py
haunt/operations/__init__.py
haunt/operations/install.py
haunt/operations/uninstall.py
haunt-0.2.0.dist-info/METADATA
haunt-0.2.0.dist-info/WHEEL
haunt-0.2.0.dist-info/entry_points.txt
haunt-0.2.0.dist-info/licenses/LICENSE
haunt-0.2.0.dist-info/RECORD
