Metadata-Version: 2.4
Name: haunt
Version: 0.2.0
Summary: Symlink dotfiles manager
Project-URL: Homepage, https://github.com/mikepqr/haunt
Project-URL: Repository, https://github.com/mikepqr/haunt
Project-URL: Issues, https://github.com/mikepqr/haunt/issues
Author-email: Mike Lee Williams <mike@mike.place>
License: MIT
License-File: LICENSE
Keywords: dotfiles,symlink
Classifier: Development Status :: 3 - Alpha
Classifier: Intended Audience :: Developers
Classifier: License :: OSI Approved :: MIT License
Classifier: Programming Language :: Python :: 3
Classifier: Programming Language :: Python :: 3.12
Classifier: Programming Language :: Python :: 3.13
Classifier: Programming Language :: Python :: 3.14
Requires-Python: >=3.12
Requires-Dist: platformdirs>=4.0.0
Requires-Dist: typer>=0.9.0
